{"lang":"ja","page":{"pageTitle":"サービスの更新","pageSubtitle":"2026年6月7日開始","introP1":"2026年6月7日より、Metroでは市内全域の利用者に向けた運行の信頼性向上を目的として、バスおよび鉄道サービスの見直しを実施します。","introP2":"最新のサービスアップデートの概要は、次の言語でPDFをダウンロードすることができます。","download":"ダウンロード","lineListTitle":"サービスアップデートのあるバスライン：","update":"アップデート：","reason":"理由：","schedule":"新スケジュール","map":"地図を見る","privacy":"プライバシーポリシー","terms":"利用規約","contact":"お問い合わせ","showTranslateButton":"TRUE","translate":"翻訳","top":"Back to top","selectLanguage":"言語を選択する","takeone_label_en":"English","takeone_label_es":"Español (Spanish)","takeone_label_hy":"հայերեն (Armenian)","takeone_label_zh-tw":"中文 (Chinese Traditional)","takeone_label_ko":"한국어 (Korean)","takeone_label_ja":"日本語 (Japanese)","takeone_label_ru":"русский (Russian)","takeone_label_vi":"Tiếng Việt (Vietnamese)","takeone_file_en":"","takeone_file_es":"","takeone_file_hy":"","takeone_file_zh-tw":"","takeone_file_ko":"","takeone_file_ja":"","takeone_file_ru":"","takeone_file_vi":""},"updates":{"2":{"update":"平日および土曜日のダイヤでは、所要時間の調整が行われます。また、通常の利用者数に対して運行本数が大幅に多い一部の便については減便を実施し、その中には平日午前5時台の東行き1便の廃止も含まれます。","reason":"実際の所要時間をより正確に反映し、運行の信頼性を向上させるため。\n追加の輸送余力を確保し、慢性的な混雑を回避するため、一部便を減便。","map":"","schedule":"2_TT_06-07-26.pdf","description":"Westwood - USC","lineLabel":"","arterials":"Sunset Bl"},"10":{"update":"平日および土曜日のダイヤでは、所要時間の調整を行います。","reason":"実際の所要時間をより正確に反映し、運行の信頼性を向上させるため。","map":"","schedule":"10_TT_06-07-26.pdf","description":"West Hollywood - Downtown LA","lineLabel":"","arterials":"Temple St, Melrose Av"},"28":{"update":"平日および土曜日のダイヤでは、所要時間の調整を行います。また、通常の利用者数に対して運行本数が大幅に多い一部の便については減便を実施し、その中には平日午前9時台の東行き1便および平日午後6時台の西行き1便の廃止も含まれます。","reason":"実際の所要時間をより正確に反映し、運行の信頼性を向上させるため。\n輸送余力を確保し、慢性的な混雑を回避するため、一部便を減便。","map":"","schedule":"28_TT_06-07-26.pdf","description":"Century City - Downtown LA","lineLabel":"","arterials":"Olympic Bl"},"30":{"update":"土曜日ダイヤのみ、所要時間の調整を行います。","reason":"実際の所要時間をより正確に反映し、運行の信頼性を向上させるため。","map":"","schedule":"30_TT_06-07-26.pdf","description":"Pico Rimpau Transit Center - Little Tokyo Station","lineLabel":"","arterials":"Pico Bl"},"33":{"update":"平日および土曜日のダイヤでは、所要時間の調整を行います。","reason":"実際の所要時間をより正確に反映し、運行の信頼性を向上させるため。","map":"","schedule":"33_TT_06-07-26.pdf","description":"Santa Monica - Downtown LA","lineLabel":"","arterials":"Venice Bl"},"35":{"update":"平日ダイヤのみ、所要時間の調整を行います。","reason":"実際の所要時間をより正確に反映し、運行の信頼性を向上させるため。","map":"","schedule":"35_TT_06-07-26.pdf","description":"Downtown LA - Washington/Fairfax Transit Hub","lineLabel":"","arterials":"Washington Bl"},"38":{"update":"平日ダイヤのみ、所要時間の調整を行います。","reason":"実際の所要時間をより正確に反映し、運行の信頼性を向上させるため。","map":"","schedule":"38_TT_06-07-26.pdf","description":"Washington/Fairfax - Downtown LA","lineLabel":"","arterials":"Jefferson Bl"},"45":{"update":"土曜日ダイヤのみ、所要時間の調整を行います。","reason":"実際の所要時間をより正確に反映し、運行の信頼性を向上させるため。","map":"","schedule":"45_TT_06-07-26.pdf","description":"Harbor Freeway Station - Lincoln Heights","lineLabel":"","arterials":"Broadway"},"48":{"update":"平日および土曜日のダイヤでは、所要時間の調整を行います。また、午前6時30分から7時30分の間に南行き2便、ならびにSan Pedro / Manchester発午前8時45分の北行き1便を追加します。","reason":"実際の所要時間をより正確に反映し、運行の信頼性を向上させるため。\n輸送力を強化し、慢性的な混雑を回避するため、便を追加。","map":"","schedule":"48_TT_06-07-26.pdf","description":"Downtown LA - Avalon Station","lineLabel":"","arterials":"Main St, South San Pedro St"},"51":{"update":"平日・土曜日・日曜日のダイヤでは、所要時間の調整を行います。平日については、上下線ともに朝夕のラッシュ時間帯に運行間隔を5.5〜7.5分へ変更することに伴い、一部減便を実施します。","reason":"実際の所要時間をより正確に反映し、運行の信頼性を向上させるため。\n輸送余力を確保し、慢性的な混雑を回避するため、一部便を減便。","map":"","schedule":"51_TT_06-07-26.pdf","description":"CSU Dominguez Hills - Westlake/MacArthur Park Station","lineLabel":"","arterials":"7th St, Avalon Bl"},"53":{"update":"平日・土曜日・日曜日のダイヤでは、所要時間の調整を行います。","reason":"実際の所要時間をより正確に反映し、運行の信頼性を向上させるため。","map":"","schedule":"53_TT_06-07-26.pdf","description":"CSU Dominguez Hills - Downtown LA","lineLabel":"","arterials":"Central Av"},"60":{"update":"平日・土曜日・日曜日のダイヤでは、所要時間の調整を行います。","reason":"実際の所要時間をより正確に反映し、運行の信頼性を向上させるため。","map":"","schedule":"60_TT_06-07-26.pdf","description":"Artesia Station - Downtown LA","lineLabel":"","arterials":"Long Beach Bl"},"62":{"update":"平日・土曜日・日曜日のダイヤでは、所要時間の調整を行います。","reason":"実際の所要時間をより正確に反映し、運行の信頼性を向上させるため。","map":"","schedule":"62_TT_06-07-26.pdf","description":"Hawaiian Gardens - Downtown LA","lineLabel":"","arterials":"Telegraph Rd"},"66":{"update":"平日・土曜日・日曜日のダイヤでは、所要時間の調整を行います。","reason":"実際の所要時間をより正確に反映し、運行の信頼性を向上させるため。","map":"","schedule":"66_TT_06-07-26.pdf","description":"Wilshire Center - Montebello Metrolink Station","lineLabel":"","arterials":"8th St, Olympic Bl"},"70":{"update":"平日ダイヤのみ、所要時間の調整を行います。","reason":"実際の所要時間をより正確に反映し、運行の信頼性を向上させるため。","map":"","schedule":"70_TT_06-07-26.pdf","description":"Downtown LA - El Monte","lineLabel":"","arterials":"Cesar Chavez Av, Atlantic Bl, Garvey Av"},"76":{"update":"土曜日ダイヤのみ、所要時間の調整を行います。","reason":"実際の所要時間をより正確に反映し、運行の信頼性を向上させるため。","map":"","schedule":"76_TT_06-07-26.pdf","description":"Downtown LA - El Monte","lineLabel":"","arterials":"Valley Bl"},"78":{"update":"平日および土曜日のダイヤでは、所要時間の調整を行います。","reason":"実際の所要時間をより正確に反映し、運行の信頼性を向上させるため。","map":"","schedule":"78_TT_06-07-26.pdf","description":"Downtown LA - Arcadia","lineLabel":"","arterials":"Las Tunas Av, Huntington Dr"},"81":{"update":"土曜日ダイヤのみ、所要時間の調整を行います。","reason":"実際の所要時間をより正確に反映し、運行の信頼性を向上させるため。","map":"","schedule":"81_TT_06-07-26.pdf","description":"Eagle Rock - Harbor Freeway Station","lineLabel":"","arterials":"Figueroa St"},"102":{"update":"平日ダイヤのみ、所要時間の調整を行います。","reason":"実際の所要時間をより正確に反映し、運行の信頼性を向上させるため。","map":"","schedule":"102_TT_06-07-26.pdf","description":"LAX City Bus Center - South Gate","lineLabel":"","arterials":"La Tijera Bl, Exposition Bl"},"105":{"update":"平日ダイヤのみ、所要時間の調整を行います。","reason":"実際の所要時間をより正確に反映し、運行の信頼性を向上させるため。","map":"","schedule":"105_TT_06-7-26.pdf","description":"Vernon - West Hollywood","lineLabel":"","arterials":"La Cienega Bl, Vernon Av"},"108":{"update":"日曜日ダイヤのみ、所要時間の調整を行います。","reason":"実際の所要時間をより正確に反映し、運行の信頼性を向上させるため。","map":"","schedule":"108_TT_6-7-26.pdf","description":"Marina Del Rey - Pico Rivera","lineLabel":"","arterials":"Slauson Av"},"110":{"update":"土曜日および日曜日のダイヤでは、所要時間の調整を行います。","reason":"実際の所要時間をより正確に反映し、運行の信頼性を向上させるため。","map":"","schedule":"110_TT_06-7-26.pdf","description":"Playa Vista - Bell Gardens","lineLabel":"","arterials":"Jefferson Bl, Gage Av"},"115":{"update":"日曜日ダイヤのみ、所要時間の調整を行います。","reason":"実際の所要時間をより正確に反映し、運行の信頼性を向上させるため。","map":"","schedule":"115_TT_06-7-26.pdf","description":"Playa Del Rey - Norwalk","lineLabel":"","arterials":"Manchester Av, Firestone Bl"},"117":{"update":"平日ダイヤのみ、所要時間の調整を行います。","reason":"実際の所要時間をより正確に反映し、運行の信頼性を向上させるため。","map":"","schedule":"117_TT_06-07-26.pdf","description":"LAX City Bus Center - Downey","lineLabel":"","arterials":"Century Bl, Imperial Hwy"},"125":{"update":"土曜日および日曜日のダイヤでは、所要時間の調整を行います。","reason":"実際の所要時間および利用状況をより正確に反映し、運行の信頼性を向上させるため。削減によって生じたコストは、他の改善施策へ再配分します。","map":"","schedule":"125_ TT_06-7-26.pdf","description":"El Segundo - Norwalk Station","lineLabel":"","arterials":"Rosecrans Av"},"134":{"update":"平日・土曜日・日曜日のダイヤでは、所要時間の調整を行います。","reason":"実際の所要時間をより正確に反映し、運行の信頼性を向上させるため。","map":"","schedule":"134_TT_06-7-26.pdf","description":"Downtown Santa Monica Station - Malibu","lineLabel":"","arterials":"Pacific Coast Hwy"},"150":{"update":"","reason":"","map":"","schedule":"150_TT_06-07-26.pdf","description":"Chatsworth - Encino","lineLabel":"","arterials":"Topanga Canyon Bl, Ventura Bl"},"152":{"update":"平日ダイヤのみ、所要時間の調整を行います。","reason":"実際の所要時間をより正確に反映し、運行の信頼性を向上させるため。","map":"","schedule":"152_TT_06-07-26.pdf","description":"West Hills Medical Center - North Hollywood Station","lineLabel":"","arterials":"Roscoe Bl"},"155":{"update":"平日・土曜日・日曜日のダイヤでは、所要時間の調整を行います。","reason":"実際の所要時間をより正確に反映し、運行の信頼性を向上させるため。","map":"","schedule":"155_TT_06-07-26.pdf","description":"Burbank Station - North Hollywood Station","lineLabel":"","arterials":"Riverside Dr, Olive St"},"161":{"update":"平日・土曜日・日曜日のダイヤでは、所要時間の調整を行います。","reason":"実際の所要時間をより正確に反映し、運行の信頼性を向上させるため。","map":"","schedule":"161_TT_06-07-26.pdf","description":"Thousand Oaks - Canoga Station","lineLabel":"","arterials":"Westlake Village, Agoura Hills, Calabasas"},"162":{"update":"経路および停留所の変更：実際の所要時間をより正確に反映し、運行の信頼性を向上させるため。輸送余力を確保し、慢性的な混雑を回避するため、一部便を減便。","reason":"工事によるサービスへの影響に対応するため、必要な変更を実施します。","map":"","schedule":"162_TT_06-07-26.pdf","description":"Woodland Hills - North Hollywood","lineLabel":"","arterials":"Sherman Wy, Vineland Av"},"166":{"update":"平日ダイヤのみ、所要時間の調整を行います。平日午後2時台には、東行き1便を追加します。","reason":"実際の所要時間をより正確に反映し、運行の信頼性を向上させるため。\n輸送余力を確保し、慢性的な混雑を回避するため、便を追加。","map":"","schedule":"166_TT_06-07-26.pdf","description":"Chatsworth - Sun Valley","lineLabel":"","arterials":"Nordhoff St, Osborne St"},"167":{"update":"平日ダイヤのみ、所要時間の調整を行います。","reason":"実際の所要時間をより正確に反映し、運行の信頼性を向上させるため。","map":"","schedule":"167_TT_06-07-26.pdf","description":"Chatsworth Station - Studio City","lineLabel":"","arterials":"Plummer, Coldwater Canyon"},"204":{"update":"平日および土曜日のダイヤでは、所要時間の調整を行います。平日については、上下線ともに朝夕のラッシュ時間帯に運行間隔を5.5〜7.5分へ変更することに伴い、一部減便を実施します。さらに、平日午後6時台の北行き1便、平日午後7時台の南行き1便、および土曜日午後6時台の北行き1便を減便します。","reason":"実際の所要時間をより正確に反映し、運行の信頼性を向上させるため。\n輸送余力を確保し、慢性的な混雑を回避するため、一部便を減便。","map":"","schedule":"204_TT_06_07_26.pdf","description":"Vermont/Athens Station - Hollywood","lineLabel":"","arterials":"Vermont Av"},"206":{"update":"日曜日ダイヤのみ、所要時間の調整を行います。","reason":"実際の所要時間をより正確に反映し、運行の信頼性を向上させるため。","map":"","schedule":"206_TT_06-07-26.pdf","description":"Vermont/Athens Station - Hollywood","lineLabel":"","arterials":"Normandie Av"},"217":{"update":"平日および土曜日のダイヤでは、所要時間の調整を行います。","reason":"実際の所要時間をより正確に反映し、運行の信頼性を向上させるため。","map":"","schedule":"217_TT_06-7-26.pdf","description":"La Cienega Station - Vermont/Sunset Station","lineLabel":"","arterials":"Hollywood Bl, Fairfax Av"},"222":{"update":"平日・土曜日・日曜日のダイヤでは、所要時間の調整を行います。","reason":"実際の所要時間をより正確に反映し、運行の信頼性を向上させるため。","map":"","schedule":"222_TT_06-07-26.pdf","description":"Hollywood - Sun Valley","lineLabel":"","arterials":"Hollywood Wy, Riverside Dr"},"233":{"update":"平日ダイヤのみ、所要時間の調整を行います。","reason":"実際の所要時間をより正確に反映し、運行の信頼性を向上させるため。","map":"","schedule":"233_TT_06-07-26.pdf","description":"Sherman Oaks - Lakeview Terrace","lineLabel":"","arterials":"Van Nuys Bl"},"240":{"update":"平日ダイヤのみ、所要時間の調整を行います。","reason":"実際の所要時間をより正確に反映し、運行の信頼性を向上させるため。","map":"","schedule":"240_TT_06-07-26.pdf","description":"Northridge - Universal/Studio City Station","lineLabel":"","arterials":"Reseda Bl, Ventura Bl"},"242":{"update":"平日ダイヤのみ、所要時間の調整を行います。","reason":"実際の所要時間をより正確に反映し、運行の信頼性を向上させるため。","map":"","schedule":"242-243_TT_06-07-26.pdf","description":"Tarzana - Northridge","lineLabel":"","arterials":"Tampa Av"},"243":{"update":"平日ダイヤのみ、所要時間の調整を行います。","reason":"実際の所要時間をより正確に反映し、運行の信頼性を向上させるため。","map":"","schedule":"242-243_TT_06-07-26.pdf","description":"Woodland Hills - Chatsworth","lineLabel":"","arterials":"Winnetka Av"},"244":{"update":"平日：Chatsworth High Schoolの利用生徒数増加に対応するため、登校日の朝に1便を追加します。","reason":"実際の所要時間をより正確に反映し、運行の信頼性を向上させるため。\n輸送余力を確保し、慢性的な混雑を回避するため、便を追加。","map":"","schedule":"244_TT_06-07-26.pdf","description":"Woodland Hills - Chatsworth Station","lineLabel":"","arterials":"De Soto Av"},"246":{"update":"土曜日および日曜日のダイヤでは、所要時間の調整を行います。","reason":"実際の所要時間をより正確に反映し、運行の信頼性を向上させるため。","map":"","schedule":"246_TT_06-7-26.pdf","description":"San Pedro - Harbor Gateway Transit Center","lineLabel":"","arterials":"Avalon Bl"},"260":{"update":"平日および土曜日のダイヤでは、所要時間の調整を行います。","reason":"実際の所要時間をより正確に反映し、運行の信頼性を向上させるため。","map":"","schedule":"260-261_TT_6-7-26.pdf","description":"Willowbrook/Rosa Parks Station - Pasadena","lineLabel":"","arterials":"Fair Oaks Av, Atlantic Bl"},"261":{"update":"平日および土曜日のダイヤでは、所要時間の調整を行います。","reason":"実際の所要時間をより正確に反映し、運行の信頼性を向上させるため。","map":"","schedule":"260-261_TT_6-7-26.pdf","description":"Artesia Station - Pasadena","lineLabel":"","arterials":"Fair Oaks Av, Atlantic Bl"},"265":{"update":"平日および土曜日のダイヤでは、所要時間の調整を行います。","reason":"実際の所要時間をより正確に反映し、運行の信頼性を向上させるため。","map":"","schedule":"265_TT_6-7-26.pdf","description":"Lakewood Center Mall - Pico Rivera","lineLabel":"","arterials":"Paramount Bl"},"266":{"update":"平日および土曜日のダイヤでは、所要時間の調整を行います。","reason":"実際の所要時間をより正確に反映し、運行の信頼性を向上させるため。","map":"","schedule":"266_TT_06-7-26.pdf","description":"Lakewood Center Mall - Sierra Madre Villa Station","lineLabel":"","arterials":"Rosemead Bl"},"268":{"update":"","reason":"","map":"","schedule":"268_TT_06-7-26.pdf","description":"El Monte Station - Sierra Madre Villa Station","lineLabel":"","arterials":"Baldwin Av"},"287":{"update":"","reason":"","map":"","schedule":"287 TT 6-7-26.pdf","description":"The Shops at Montebello - Arcadia Station","lineLabel":"","arterials":"Santa Anita Av"},"460":{"update":"平日・土曜日・日曜日のダイヤでは、所要時間の調整を行います。","reason":"実際の所要時間をより正確に反映し、運行の信頼性を向上させるため。","map":"","schedule":"460_TT_06-7-26.pdf","description":"Downtown LA - Disneyland","lineLabel":"","arterials":"I-110 Freeway, I-105 Freeway"},"487":{"update":"平日および土曜日のダイヤでは、所要時間の調整を行います。","reason":"実際の所要時間をより正確に反映し、運行の信頼性を向上させるため。","map":"","schedule":"487-489_TT_6-7-26.pdf","description":"Downtown LA - Sierra Madre Villa Station","lineLabel":"","arterials":""},"489":{"update":"平日および土曜日のダイヤでは、所要時間の調整を行います。また、午後6時台に東行き1便を追加します。","reason":"実際の所要時間をより正確に反映し、運行の信頼性を向上させるため。\n輸送余力を確保し、慢性的な混雑を回避するため、便を追加。","map":"","schedule":"487-489_TT_6-7-26.pdf","description":"Downtown LA - Temple City","lineLabel":"","arterials":""},"602":{"update":"平日ダイヤのみ、所要時間の調整を行います。","reason":"実際の所要時間をより正確に反映し、運行の信頼性を向上させるため。","map":"","schedule":"602_TT_06-7-26.pdf","description":"Pacific Palisades - Westwood","lineLabel":"","arterials":"Sunset Bl"},"662":{"update":"平日・土曜日・日曜日のダイヤでは、所要時間の調整を行います。","reason":"実際の所要時間をより正確に反映し、運行の信頼性を向上させるため。","map":"","schedule":"662_TT_06-07-26.pdf","description":"Altadena - Pasadena Shuttle","lineLabel":"Altadena - Pasadena Shuttle","arterials":"Lake Av, Los Robles Av, Lincoln Av"},"665":{"update":"平日ダイヤのみ、所要時間の調整を行います。","reason":"実際の所要時間をより正確に反映し、運行の信頼性を向上させるため。","map":"","schedule":"665_TT_6-7-26.pdf","description":"Cal State LA - Indiana Station","lineLabel":"CalState LA - City Terrace Shuttle","arterials":"Indiana St, Gage Ave, Eastern"},"754":{"update":"土曜日ダイヤのみ、所要時間の調整を行います。","reason":"実際の所要時間をより正確に反映し、運行の信頼性を向上させるため。","map":"","schedule":"754_TT_6-7-26.pdf","description":"Vermont/Athens Station - Hollywood","lineLabel":"","arterials":"Vermont Av"},"761":{"update":"平日・土曜日・日曜日のダイヤでは、所要時間の調整を行います。","reason":"実際の所要時間をより正確に反映し、運行の信頼性を向上させるため。","map":"","schedule":"761_TT_06-07-26.pdf","description":"Expo/Sepulveda Station - Sylmar Station","lineLabel":"","arterials":"San Fernando Bl, Van Nuys Bl, Sepulveda Bl"},"910":{"update":"平日・土曜日・日曜日のダイヤでは、所要時間の調整を行います。また、午前11時40分発の北行き1便を追加します。","reason":"実際の所要時間をより正確に反映し、運行の信頼性を向上させるため。\n輸送余力を確保し、慢性的な混雑を回避するため、便を追加。","map":"","schedule":"910_TT _6_7_26.pdf","description":"Harbor Gateway - El Monte","lineLabel":"J Line","arterials":""},"950":{"update":"平日・土曜日・日曜日のダイヤでは、所要時間の調整を行います。","reason":"実際の所要時間をより正確に反映し、運行の信頼性を向上させるため。","map":"","schedule":"","description":"San Pedro - El Monte","lineLabel":"J Line","arterials":""}},"lineList":["2","10","28","30","33","35","38","45","48","51","53","60","62","66","70","76","78","81","102","105","108","110","115","117","125","134","150","152","155","161","162","166","167","204","206","217","222","233","240","242","243","244","246","260","261","265","266","268","287","460","487","489","602","662","665","754","761","910","950"]}